LICENSE
MANIFEST.in
README.md
setup.py
librapythonpro/__init__.py
librapythonpro/github_api.py
librapythonpro.egg-info/PKG-INFO
librapythonpro.egg-info/SOURCES.txt
librapythonpro.egg-info/dependency_links.txt
librapythonpro.egg-info/not-zip-safe
librapythonpro.egg-info/requires.txt
librapythonpro.egg-info/top_level.txt